uweb3/__init__.py
uweb3/alchemy_model.py
uweb3/connections.py
uweb3/model.py
uweb3/request.py
uweb3/response.py
uweb3/sockets.py
uweb3/templateparser.py
uweb3/connectors/Mongo.py
uweb3/connectors/Mysql.py
uweb3/connectors/SignedCookie.py
uweb3/connectors/SqlAlchemy.py
uweb3/connectors/Sqlite.py
uweb3/connectors/__init__.py
uweb3/libs/__init__.py
uweb3/libs/mail.py
uweb3/libs/utils.py
uweb3/libs/safestring/__init__.py
uweb3/libs/safestring/test.py
uweb3/libs/sqltalk/__init__.py
uweb3/libs/sqltalk/sqlresult.py
uweb3/libs/sqltalk/sqlresult_test.py
uweb3/libs/sqltalk/mysql/__init__.py
uweb3/libs/sqltalk/mysql/connection.py
uweb3/libs/sqltalk/mysql/cursor.py
uweb3/libs/sqltalk/sqlite/__init__.py
uweb3/libs/sqltalk/sqlite/connection.py
uweb3/libs/sqltalk/sqlite/converters.py
uweb3/libs/sqltalk/sqlite/cursor.py
uweb3/pagemaker/__init__.py
uweb3/pagemaker/decorators.py
uweb3/pagemaker/http_403.html
uweb3/pagemaker/http_500.html
uWebthree-3.0.4.dist-info/LICENSE
uWebthree-3.0.4.dist-info/METADATA
uWebthree-3.0.4.dist-info/WHEEL
uWebthree-3.0.4.dist-info/top_level.txt
uWebthree-3.0.4.dist-info/RECORD
