Metadata-Version: 2.1
Name: uWebthree
Version: 3.0.4
Summary: uWeb, python3, uswgi compatible micro web platform
Home-page: https://github.com/underdark.nl/uweb3
Author: Jan Klopper
Author-email: jan@underdark.nl
License: ISC
Keywords: minimal python web framework
Platform: UNKNOWN
Classifier: Development Status :: 4 - Beta
Classifier: Intended Audience :: Developers
Classifier: Environment :: Web Environment
Classifier: License :: OSI Approved :: ISC License (ISCL)
Classifier: Operating System :: POSIX :: Linux
Classifier: Programming Language :: Python
Classifier: Programming Language :: Python :: 3
Requires-Python: >=3.5
Requires-Dist: PyMySQL
Requires-Dist: pytz
